<?xml version="1.0" encoding="utf-8" standalone="yes" ?>
<T3locallang>
    <meta type="array">
        <description></description>
        <type>CSH</type>
        <csh_table>tt_products_cat</csh_table>
        <labelContext type="array">
        </labelContext>
    </meta>
    <data type="array">
        <languageKey index="default" type="array">
            <label index=".description">Shop items categories.</label>
            <label index=".details">The categories are only used with the shopping system if the shop is configured to do so.</label>
            <label index="_.seeAlso">tt_products</label>
            <label index="title.description">[FILL IN] tt_products_cat-&gt;title</label>
        </languageKey>
        <languageKey index="de" type="array">
            <label index=".description">Produktkategorien</label>
            <label index=".details">Die Kategorien werden im Shop System nur dann verwendet, wenn der Shop auch dafür konfiguriert worden ist.</label>
        </languageKey>
        <languageKey index="fi" type="array">
            <label index=".description">Tuotteiden kategoriat.</label>
            <label index=".details">Kategorioita käytetään vain, jos tuotteet on konfiguroitu käyttämään niitä.</label>
        </languageKey>
        <languageKey index="fr" type="array">
            <label index=".description">Catégories du magasin.</label>
            <label index=".details">Les catégories ne sont utilisées que si le plugin est configuré.</label>
        </languageKey>
        <languageKey index="hr" type="array">
            <label index=".description">Kategorije ugraÄ‘enog sustava za prodaju</label>
            <label index=".details">Ove se kategosije koriste samo ako je sustav za prodaju iskonfiguriran da ih koristi</label>
        </languageKey>
        <languageKey index="it" type="array">
            <label index=".description">Categorie dello Shop</label>
            <label index=".details">Le categorie sono usate solo se lo shop è adeguatamente configurato</label>
        </languageKey>
        <languageKey index="no" type="array">
            <label index=".description">Kategorier for innebygde butikkprodukter.</label>
            <label index=".details">Kategoriene vises bare i butikksystemet hvis det er konfigurert slik.</label>
        </languageKey>
    </data>
    <orig_hash type="array">
        <languageKey index="default" type="array">
            <label index=".description" type="integer">215823510</label>
            <label index=".details" type="integer">146513218</label>
            <label index="_.seeAlso" type="integer">6850969</label>
            <label index="title.description" type="integer">189401540</label>
        </languageKey>
        <languageKey index="de" type="array">
            <label index=".description" type="integer">215823510</label>
            <label index=".details" type="integer">146513218</label>
        </languageKey>
        <languageKey index="fi" type="array">
            <label index=".description" type="integer">215823510</label>
            <label index=".details" type="integer">146513218</label>
        </languageKey>
        <languageKey index="fr" type="array">
            <label index=".description" type="integer">215823510</label>
            <label index=".details" type="integer">146513218</label>
        </languageKey>
        <languageKey index="hr" type="array">
            <label index=".description" type="integer">215823510</label>
            <label index=".details" type="integer">146513218</label>
        </languageKey>
        <languageKey index="it" type="array">
            <label index=".description" type="integer">215823510</label>
            <label index=".details" type="integer">146513218</label>
        </languageKey>
        <languageKey index="no" type="array">
            <label index=".description" type="integer">215823510</label>
            <label index=".details" type="integer">146513218</label>
        </languageKey>
    </orig_hash>
    <orig_text type="array">
        <languageKey index="default" type="array">
        </languageKey>
        <languageKey index="de" type="array">
        </languageKey>
        <languageKey index="fi" type="array">
        </languageKey>
        <languageKey index="fr" type="array">
        </languageKey>
        <languageKey index="hr" type="array">
        </languageKey>
        <languageKey index="it" type="array">
        </languageKey>
        <languageKey index="no" type="array">
        </languageKey>
    </orig_text>
</T3locallang>